{
    "patient": {
        "personIdCardModels": [],
        "addressModels": [
            {
                "addrTypeRefId": "6",
                "street1": "444 Moore Pass",
                "street2": "Skiles Orchard",
                "city": "Tottenham Leopoldotown",
                "state": "736",
                "zip": "727",
                "zip4": ""
            }
        ],
        "communicationModels": [
            {
                "commTypeRefId": "14",
                "commValue": "876-358-0447"
            }
        ],
        "ssn": "5555777",
        "firstName": "Thomas",
        "billingFirstName": "Earn",
        "lastName": "Partey",
        "billingLastName": "Kutcher",
        "middleName": "Toni",
        "billingMiddleName": "Ozil",
        "dob": "1990-12-14T17:00:00.000Z",
        "billingDob": "1990-12-14T17:00:00.000Z",
        "adminGenderRefId": "10",
        "genderAtBirthRefId": "10",
        "idCardTypeRefId": "",
        "idNumber": "",
        "preferredCommRefId": "14"
    },
    "byPassDeduplication": false
}
